metspy/__init__.py
metspy/config.py
metspy/dispatcher.py
metspy/example.py
metspy/initializer.py
metspy/processor.py
metspy/spyder.py
metspy-0.1.10.dist-info/DESCRIPTION.rst
metspy-0.1.10.dist-info/METADATA
metspy-0.1.10.dist-info/RECORD
metspy-0.1.10.dist-info/WHEEL
metspy-0.1.10.dist-info/metadata.json
metspy-0.1.10.dist-info/top_level.txt
