Metadata-Version: 2.0
Name: metspy
Version: 0.1.10
Summary: Scraping AQI, PM2.5 and meteorological parameters
Home-page: https://github.com/soonyenju/metSpy
Author: soonyenju
Author-email: soonyenju@foxmail.com
License: MIT Licence
Keywords: pip,meteorology,scraping,aqi,soonyenju
Platform: any
